{
  "parent": "minecraft:recipes/root",
  "criteria": {
    "has_prismatic_core": {
      "trigger": "minecraft:inventory_changed",
      "conditions": {
        "items": [
          {
            "items": [
              "gatewayexpansion:prismatic_core"
            ]
          }
        ]
      }
    },
    "has_the_recipe": {
      "trigger": "minecraft:recipe_unlocked",
      "conditions": {
        "recipe": "gatewayexpansion:tier_5_crystal"
      }
    }
  },
  "requirements": [
    [
      "has_prismatic_core",
      "has_the_recipe"
    ]
  ],
  "rewards": {
    "recipes": [
      "gatewayexpansion:tier_5_crystal"
    ]
  }
}
